odoo/addons/sale_stock_available_to_promise_release/README.rst
odoo/addons/sale_stock_available_to_promise_release/__init__.py
odoo/addons/sale_stock_available_to_promise_release/__manifest__.py
odoo/addons/sale_stock_available_to_promise_release/i18n/ca.po
odoo/addons/sale_stock_available_to_promise_release/i18n/de.po
odoo/addons/sale_stock_available_to_promise_release/i18n/es_AR.po
odoo/addons/sale_stock_available_to_promise_release/i18n/fr.po
odoo/addons/sale_stock_available_to_promise_release/i18n/it.po
odoo/addons/sale_stock_available_to_promise_release/i18n/sale_stock_available_to_promise_release.pot
odoo/addons/sale_stock_available_to_promise_release/models/__init__.py
odoo/addons/sale_stock_available_to_promise_release/models/procurement_group.py
odoo/addons/sale_stock_available_to_promise_release/models/product_product.py
odoo/addons/sale_stock_available_to_promise_release/models/sale_order.py
odoo/addons/sale_stock_available_to_promise_release/models/sale_order_line.py
odoo/addons/sale_stock_available_to_promise_release/models/stock_move.py
odoo/addons/sale_stock_available_to_promise_release/models/stock_picking.py
odoo/addons/sale_stock_available_to_promise_release/readme/CONTRIBUTORS.rst
odoo/addons/sale_stock_available_to_promise_release/readme/DESCRIPTION.rst
odoo/addons/sale_stock_available_to_promise_release/reports/sale_order.xml
odoo/addons/sale_stock_available_to_promise_release/static/description/icon.png
odoo/addons/sale_stock_available_to_promise_release/static/description/index.html
odoo/addons/sale_stock_available_to_promise_release/tests/__init__.py
odoo/addons/sale_stock_available_to_promise_release/tests/test_sale_line_availability_status.py
odoo/addons/sale_stock_available_to_promise_release/views/product_product_views.xml
odoo/addons/sale_stock_available_to_promise_release/views/sale_order_views.xml
odoo/addons/sale_stock_available_to_promise_release/views/stock_move_views.xml
odoo13_addon_sale_stock_available_to_promise_release-13.0.1.7.0.dist-info/METADATA
odoo13_addon_sale_stock_available_to_promise_release-13.0.1.7.0.dist-info/WHEEL
odoo13_addon_sale_stock_available_to_promise_release-13.0.1.7.0.dist-info/top_level.txt
odoo13_addon_sale_stock_available_to_promise_release-13.0.1.7.0.dist-info/RECORD
